{
  "datetime": "2025-11-20T13:38:29.024000Z",
  "platform": "Sentinel-2B",
  "instruments": [
    "msi"
  ],
  "s2:mgrs_tile": "21JYM",
  "constellation": "Sentinel 2",
  "s2:granule_id": "S2B_OPER_MSI_L2A_TL_2BPS_20251120T153855_A045481_T21JYM_N05.11",
  "eo:cloud_cover": 0.001616,
  "s2:datatake_id": "GS2B_20251120T133829_045481_N05.11",
  "s2:product_uri": "S2B_MSIL2A_20251120T133829_N0511_R124_T21JYM_20251120T153855.SAFE",
  "s2:datastrip_id": "S2B_OPER_MSI_L2A_DS_2BPS_20251120T153855_S20251120T133828_N05.11",
  "s2:product_type": "S2MSI2A",
  "sat:orbit_state": "descending",
  "s2:datatake_type": "INS-NOBS",
  "s2:generation_time": "2025-11-20T15:38:55.000000Z",
  "sat:relative_orbit": 124,
  "s2:water_percentage": 3.572994,
  "s2:mean_solar_zenith": 22.4211492634071,
  "s2:mean_solar_azimuth": 79.4186021741808,
  "s2:processing_baseline": "05.11",
  "s2:snow_ice_percentage": 0.0,
  "s2:vegetation_percentage": 89.66521,
  "s2:thin_cirrus_percentage": 0.001609,
  "s2:cloud_shadow_percentage": 0.0,
  "s2:nodata_pixel_percentage": 0.0,
  "s2:unclassified_percentage": 0.141118,
  "s2:not_vegetated_percentage": 6.48681,
  "s2:degraded_msi_data_percentage": 0.0218,
  "s2:high_proba_clouds_percentage": 0.0,
  "s2:reflectance_conversion_factor": 1.02315025801053,
  "s2:medium_proba_clouds_percentage": 7e-06,
  "s2:saturated_defective_pixel_percentage": 0.0,
  "proj:code": "EPSG:32721",
  "id": "S2B_MSIL2A_20251120T133829_R124_T21JYM_20251120T153855"
}